{"credit":"Made with Blockbench","textures":{"0":"./kimotara","particle":"./kimotara"},"elements":[{"from":[6,1.5,0],"to":[8,14.5,0.5],"faces":{"north":{"uv":[8,1.5,6,14.5],"texture":"#0"},"east":{"uv":[7.5,1.5,8,14.5],"texture":"#0"},"south":{"uv":[6,1.5,8,14.5],"texture":"#0"},"west":{"uv":[6,1.5,6.5,14.5],"texture":"#0"},"up":{"uv":[6,1.5,8,2],"texture":"#0"},"down":{"uv":[6,14,8,14.5],"texture":"#0"}}},{"from":[5,1.5,0],"to":[6,14,0.5],"faces":{"north":{"uv":[6,2,5,14.5],"texture":"#0"},"south":{"uv":[5,2,6,14.5],"texture":"#0"},"west":{"uv":[5,2,5.5,14.5],"texture":"#0"},"up":{"uv":[5,2,6,2.5],"texture":"#0"},"down":{"uv":[5,14,6,14.5],"texture":"#0"}}},{"from":[8,1,0],"to":[10,14,0.5],"faces":{"north":{"uv":[10,2,8,15],"texture":"#0"},"east":{"uv":[9.5,2,10,15],"texture":"#0"},"south":{"uv":[8,2,10,15],"texture":"#0"},"up":{"uv":[8,2,10,2.5],"texture":"#0"},"down":{"uv":[8,14.5,10,15],"texture":"#0"}}},{"from":[4.5,2,0],"to":[5,13.5,0.5],"faces":{"north":{"uv":[5,2.5,4.5,14],"texture":"#0"},"south":{"uv":[4.5,2.5,5,14],"texture":"#0"},"west":{"uv":[4.5,2.5,5,14],"texture":"#0"},"up":{"uv":[4.5,2.5,5,3],"texture":"#0"},"down":{"uv":[4.5,13.5,5,14],"texture":"#0"}}},{"from":[10,1,0],"to":[12,13.5,0.5],"faces":{"north":{"uv":[12,2.5,10,15],"texture":"#0"},"east":{"uv":[11.5,2.5,12,15],"texture":"#0"},"south":{"uv":[10,2.5,12,15],"texture":"#0"},"up":{"uv":[10,2.5,12,3],"texture":"#0"},"down":{"uv":[10,14.5,12,15],"texture":"#0"}}},{"from":[4,2,0],"to":[4.5,13,0.5],"faces":{"north":{"uv":[4.5,3,4,14],"texture":"#0"},"south":{"uv":[4,3,4.5,14],"texture":"#0"},"west":{"uv":[4,3,4.5,14],"texture":"#0"},"up":{"uv":[4,3,4.5,3.5],"texture":"#0"},"down":{"uv":[4,13.5,4.5,14],"texture":"#0"}}},{"from":[12,2,0],"to":[13.5,13,0.5],"faces":{"north":{"uv":[13.5,3,12,14],"texture":"#0"},"east":{"uv":[13,3,13.5,14],"texture":"#0"},"south":{"uv":[12,3,13.5,14],"texture":"#0"},"up":{"uv":[12,3,13.5,3.5],"texture":"#0"},"down":{"uv":[12,13.5,13.5,14],"texture":"#0"}}},{"from":[13.5,3,0],"to":[14,12.5,0.5],"faces":{"north":{"uv":[14,3.5,13.5,13],"texture":"#0"},"east":{"uv":[13.5,3.5,14,13],"texture":"#0"},"south":{"uv":[13.5,3.5,14,13],"texture":"#0"},"up":{"uv":[13.5,3.5,14,4],"texture":"#0"},"down":{"uv":[13.5,12.5,14,13],"texture":"#0"}}},{"from":[3.5,2,0],"to":[4,12,0.5],"faces":{"north":{"uv":[4,4,3.5,14],"texture":"#0"},"south":{"uv":[3.5,4,4,14],"texture":"#0"},"west":{"uv":[3.5,4,4,14],"texture":"#0"},"up":{"uv":[3.5,4,4,4.5],"texture":"#0"},"down":{"uv":[3.5,13.5,4,14],"texture":"#0"}}},{"from":[14,4.5,0],"to":[14.5,12,0.5],"faces":{"north":{"uv":[14.5,4,14,11.5],"texture":"#0"},"east":{"uv":[14,4,14.5,11.5],"texture":"#0"},"south":{"uv":[14,4,14.5,11.5],"texture":"#0"},"up":{"uv":[14,4,14.5,4.5],"texture":"#0"},"down":{"uv":[14,11,14.5,11.5],"texture":"#0"}}},{"from":[3,2.5,0],"to":[3.5,11.5,0.5],"faces":{"north":{"uv":[3.5,4.5,3,13.5],"texture":"#0"},"south":{"uv":[3,4.5,3.5,13.5],"texture":"#0"},"west":{"uv":[3,4.5,3.5,13.5],"texture":"#0"},"up":{"uv":[3,4.5,3.5,5],"texture":"#0"},"down":{"uv":[3,13,3.5,13.5],"texture":"#0"}}},{"from":[14.5,6.5,0],"to":[15,11.5,0.5],"faces":{"north":{"uv":[15,4.5,14.5,9.5],"texture":"#0"},"east":{"uv":[14.5,4.5,15,9.5],"texture":"#0"},"south":{"uv":[14.5,4.5,15,9.5],"texture":"#0"},"up":{"uv":[14.5,4.5,15,5],"texture":"#0"},"down":{"uv":[14.5,9,15,9.5],"texture":"#0"}}},{"from":[15,9,0],"to":[15.5,11,0.5],"faces":{"north":{"uv":[15.5,5,15,7],"texture":"#0"},"east":{"uv":[15,5,15.5,7],"texture":"#0"},"south":{"uv":[15,5,15.5,7],"texture":"#0"},"up":{"uv":[15,5,15.5,5.5],"texture":"#0"},"down":{"uv":[15,6.5,15.5,7],"texture":"#0"}}},{"from":[2.5,3,0],"to":[3,10.5,0.5],"faces":{"north":{"uv":[3,5.5,2.5,13],"texture":"#0"},"south":{"uv":[2.5,5.5,3,13],"texture":"#0"},"west":{"uv":[2.5,5.5,3,13],"texture":"#0"},"up":{"uv":[2.5,5.5,3,6],"texture":"#0"},"down":{"uv":[2.5,12.5,3,13],"texture":"#0"}}},{"from":[2,4,0],"to":[2.5,8,0.5],"faces":{"north":{"uv":[2.5,8,2,12],"texture":"#0"},"south":{"uv":[2,8,2.5,12],"texture":"#0"},"west":{"uv":[2,8,2.5,12],"texture":"#0"},"up":{"uv":[2,8,2.5,8.5],"texture":"#0"},"down":{"uv":[2,11.5,2.5,12],"texture":"#0"}}},{"from":[12,1.5,0],"to":[13,2,0.5],"faces":{"north":{"uv":[13,14,12,14.5],"texture":"#0"},"east":{"uv":[12.5,14,13,14.5],"texture":"#0"},"south":{"uv":[12,14,13,14.5],"texture":"#0"},"down":{"uv":[12,14,13,14.5],"texture":"#0"}}},{"from":[7,1,0],"to":[8,1.5,0.5],"faces":{"north":{"uv":[8,14.5,7,15],"texture":"#0"},"south":{"uv":[7,14.5,8,15],"texture":"#0"},"west":{"uv":[7,14.5,7.5,15],"texture":"#0"},"down":{"uv":[7,14.5,8,15],"texture":"#0"}}}],"gui_light":"front","display":{"thirdperson_righthand":{"rotation":[90,0,0],"translation":[-0.25,-1.75,9.75],"scale":[0.24,0.24,0.24]},"thirdperson_lefthand":{"rotation":[90,0,0],"translation":[-0.25,-1.75,9.75],"scale":[0.24,0.24,0.24]},"firstperson_righthand":{"rotation":[0,-90,25],"translation":[1.13,3.2,1.13],"scale":[0.68,0.68,0.68]},"firstperson_lefthand":{"rotation":[0,-90,25],"translation":[1.13,3.2,1.13],"scale":[0.68,0.68,0.68]},"ground":{"rotation":[0,-90,25],"translation":[1.13,3.2,1.13],"scale":[0.68,0.68,0.68]},"head":{"translation":[-3.75,-10.5,0],"scale":[0.42,0.42,0.42]},"fixed":{"translation":[0,0,8.999]}}}