{"credit":"Made with Blockbench","textures":{"0":"./top","particle":"./top_brown"},"elements":[{"from":[3,-3,9],"to":[5,32,11],"rotation":{"angle":22.5,"axis":"z","origin":[2.06833,19.81329,10]},"faces":{"north":{"uv":[14,0,16,2],"texture":"#0"},"east":{"uv":[14,0,16,2],"texture":"#0"},"south":{"uv":[14,0,16,2],"texture":"#0"},"west":{"uv":[14,0,16,2],"texture":"#0"},"up":{"uv":[14,0,16,2],"texture":"#0"},"down":{"uv":[14,0,16,2],"texture":"#0"}}},{"from":[3.59273,28.71581,9],"to":[7.59273,30.71581,11],"rotation":{"angle":45,"axis":"z","origin":[2.06833,19.81329,10]},"faces":{"north":{"uv":[14,0,16,2],"rotation":90,"texture":"#0"},"east":{"uv":[14,0,16,2],"rotation":90,"texture":"#0"},"south":{"uv":[14,0,16,2],"rotation":90,"texture":"#0"},"west":{"uv":[14,0,16,2],"rotation":90,"texture":"#0"},"up":{"uv":[14,0,16,2],"rotation":90,"texture":"#0"},"down":{"uv":[14,0,16,2],"rotation":90,"texture":"#0"}}},{"from":[-5.40449,24.37001,9],"to":[-3.40449,28.37001,11],"rotation":{"angle":-22.5,"axis":"z","origin":[-4.40449,26.37001,10]},"faces":{"north":{"uv":[14,0,16,2],"rotation":180,"texture":"#0"},"east":{"uv":[14,0,16,2],"rotation":180,"texture":"#0"},"south":{"uv":[14,0,16,2],"rotation":180,"texture":"#0"},"west":{"uv":[14,0,16,2],"rotation":180,"texture":"#0"},"up":{"uv":[14,0,16,2],"rotation":180,"texture":"#0"},"down":{"uv":[14,0,16,2],"rotation":180,"texture":"#0"}}},{"from":[-6.09373,22.65493,9],"to":[-4.09373,24.90493,11],"rotation":{"angle":0,"axis":"y","origin":[1.67691,19.81329,10]},"faces":{"north":{"uv":[14,0,16,2],"rotation":180,"texture":"#0"},"east":{"uv":[14,0,16,2],"rotation":180,"texture":"#0"},"south":{"uv":[14,0,16,2],"rotation":180,"texture":"#0"},"west":{"uv":[14,0,16,2],"rotation":180,"texture":"#0"},"up":{"uv":[14,0,16,2],"rotation":180,"texture":"#0"},"down":{"uv":[14,0,16,2],"rotation":180,"texture":"#0"}}},{"from":[-4.38498,21.56211,9],"to":[-2.38498,25.56211,11],"rotation":{"angle":22.5,"axis":"z","origin":[2.06833,19.81329,10]},"faces":{"north":{"uv":[14,0,16,2],"rotation":180,"texture":"#0"},"east":{"uv":[14,0,16,2],"rotation":180,"texture":"#0"},"south":{"uv":[14,0,16,2],"rotation":180,"texture":"#0"},"west":{"uv":[14,0,16,2],"rotation":180,"texture":"#0"},"up":{"uv":[14,0,16,2],"rotation":180,"texture":"#0"},"down":{"uv":[14,0,16,2],"rotation":180,"texture":"#0"}}},{"from":[-3.22451,19.89857,9],"to":[-1.22451,23.89857,11],"rotation":{"angle":45,"axis":"z","origin":[2.06833,19.81329,10]},"faces":{"north":{"uv":[14,0,16,2],"rotation":180,"texture":"#0"},"east":{"uv":[14,0,16,2],"rotation":180,"texture":"#0"},"south":{"uv":[14,0,16,2],"rotation":180,"texture":"#0"},"west":{"uv":[14,0,16,2],"rotation":180,"texture":"#0"},"up":{"uv":[14,0,16,2],"rotation":180,"texture":"#0"},"down":{"uv":[14,0,16,2],"rotation":180,"texture":"#0"}}},{"from":[6.72219,21.25,4.20172],"to":[11.47219,23,9.95172],"rotation":{"angle":22.5,"axis":"y","origin":[9.09719,22.125,6.76938]},"faces":{"north":{"uv":[6,8,8,10],"texture":"#0"},"east":{"uv":[6,8,8,10],"texture":"#0"},"south":{"uv":[6,8,8,10],"texture":"#0"},"west":{"uv":[6,8,8,10],"texture":"#0"},"up":{"uv":[6.25,8,9,10],"rotation":270,"texture":"#0"},"down":{"uv":[6,8,8,10],"texture":"#0"}}},{"from":[7.19617,21.25,3.043],"to":[12.94617,22.95,5.793],"rotation":{"angle":-45,"axis":"y","origin":[9.09719,22.125,6.76938]},"faces":{"north":{"uv":[6,8,8,10],"texture":"#0"},"east":{"uv":[6,8,8,10],"texture":"#0"},"south":{"uv":[6,8,8,10],"texture":"#0"},"west":{"uv":[6,8,8,10],"texture":"#0"},"up":{"uv":[6.025,8.025,8.85,9.775],"rotation":180,"texture":"#0"},"down":{"uv":[6,8,8,10],"rotation":90,"texture":"#0"}}},{"from":[5.37081,21.25,4.86836],"to":[8.12081,23,10.61836],"rotation":{"angle":0,"axis":"y","origin":[9.09719,22.125,6.76938]},"faces":{"north":{"uv":[6,8,8,10],"texture":"#0"},"east":{"uv":[6,8,8,10],"texture":"#0"},"south":{"uv":[6,8,8,10],"texture":"#0"},"west":{"uv":[6,8,8,10],"texture":"#0"},"up":{"uv":[6,8,8.85,10],"rotation":270,"texture":"#0"},"down":{"uv":[6,8,8,10],"texture":"#0"}}},{"from":[5.37081,22.71447,12.58282],"to":[6.37081,28.71447,13.58282],"rotation":{"angle":0,"axis":"y","origin":[6.74581,24.83947,13.45782]},"faces":{"north":{"uv":[10,2,12,4],"texture":"#0"},"east":{"uv":[10,2,12,4],"texture":"#0"},"south":{"uv":[10,2,12,4],"texture":"#0"},"west":{"uv":[10,2,12,4],"texture":"#0"},"up":{"uv":[10,2,12,4],"texture":"#0"},"down":{"uv":[10,2,12,4],"texture":"#0"}}},{"from":[3.37081,21.21447,11.83282],"to":[8.12081,22.21447,14.08282],"rotation":{"angle":0,"axis":"y","origin":[6.74581,25.33947,13.45782]},"faces":{"north":{"uv":[4,0,6,2],"texture":"#0"},"east":{"uv":[4,0,6,2],"texture":"#0"},"south":{"uv":[4,0,6,2],"texture":"#0"},"west":{"uv":[4,0,6,2],"texture":"#0"},"up":{"uv":[4,0,6,2],"texture":"#0"},"down":{"uv":[6,8,8,10],"texture":"#0"}}},{"from":[4.12081,22.21447,12.08282],"to":[7.62081,23.46447,13.83282],"rotation":{"angle":0,"axis":"y","origin":[6.74581,24.83947,13.45782]},"faces":{"north":{"uv":[10,2,12,4],"texture":"#0"},"east":{"uv":[10,2,12,4],"texture":"#0"},"south":{"uv":[10,2,12,4],"texture":"#0"},"west":{"uv":[10,2,12,4],"texture":"#0"},"up":{"uv":[10,2,12,4],"texture":"#0"},"down":{"uv":[10,2,12,4],"texture":"#0"}}},{"from":[3.26082,22.29476,12.58282],"to":[4.26082,25.79476,13.58282],"rotation":{"angle":22.5,"axis":"z","origin":[3.76082,25.29476,13.45782]},"faces":{"north":{"uv":[10,2,12,4],"texture":"#0"},"east":{"uv":[10,2,12,4],"texture":"#0"},"south":{"uv":[10,2,12,4],"texture":"#0"},"west":{"uv":[10,2,12,4],"texture":"#0"},"up":{"uv":[10,2,12,4],"texture":"#0"},"down":{"uv":[10,2,12,4],"texture":"#0"}}},{"from":[7.00245,22.38991,12.58282],"to":[8.00245,25.88991,13.58282],"rotation":{"angle":-22.5,"axis":"z","origin":[7.50245,24.13991,13.08282]},"faces":{"north":{"uv":[10,2,12,4],"texture":"#0"},"east":{"uv":[10,2,12,4],"texture":"#0"},"south":{"uv":[10,2,12,4],"texture":"#0"},"west":{"uv":[10,2,12,4],"texture":"#0"},"up":{"uv":[10,2,12,4],"texture":"#0"},"down":{"uv":[10,2,12,4],"texture":"#0"}}},{"from":[1.94043,25.08193,12.58282],"to":[2.94043,26.58193,13.58282],"rotation":{"angle":45,"axis":"z","origin":[2.44043,26.83193,13.45782]},"faces":{"north":{"uv":[10,2,12,4],"texture":"#0"},"east":{"uv":[10,2,12,4],"texture":"#0"},"south":{"uv":[10,2,12,4],"texture":"#0"},"west":{"uv":[10,2,12,4],"texture":"#0"},"up":{"uv":[10,2,12,4],"texture":"#0"},"down":{"uv":[10,2,12,4],"texture":"#0"}}},{"from":[7.84409,25.62482,12.58282],"to":[9.34409,26.62482,13.58282],"rotation":{"angle":45,"axis":"z","origin":[8.59409,26.12482,13.08282]},"faces":{"north":{"uv":[10,2,12,4],"rotation":90,"texture":"#0"},"east":{"uv":[10,2,12,4],"rotation":270,"texture":"#0"},"south":{"uv":[10,2,12,4],"rotation":270,"texture":"#0"},"west":{"uv":[10,2,12,4],"rotation":270,"texture":"#0"},"up":{"uv":[10,2,12,4],"rotation":270,"texture":"#0"},"down":{"uv":[10,2,12,4],"rotation":270,"texture":"#0"}}},{"from":[1.33651,26.33378,12.58282],"to":[2.83651,27.33378,13.58282],"rotation":{"angle":-22.5,"axis":"z","origin":[2.08651,26.83378,13.45782]},"faces":{"north":{"uv":[10,2,12,4],"rotation":90,"texture":"#0"},"east":{"uv":[10,2,12,4],"rotation":270,"texture":"#0"},"south":{"uv":[10,2,12,4],"rotation":270,"texture":"#0"},"west":{"uv":[10,2,12,4],"rotation":270,"texture":"#0"},"up":{"uv":[10,2,12,4],"rotation":270,"texture":"#0"},"down":{"uv":[10,2,12,4],"rotation":270,"texture":"#0"}}},{"from":[8.90511,26.33378,12.58282],"to":[10.40511,27.33378,13.58282],"rotation":{"angle":22.5,"axis":"z","origin":[9.65511,26.83378,13.08282]},"faces":{"north":{"uv":[10,2,12,4],"rotation":90,"texture":"#0"},"east":{"uv":[10,2,12,4],"rotation":270,"texture":"#0"},"south":{"uv":[10,2,12,4],"rotation":270,"texture":"#0"},"west":{"uv":[10,2,12,4],"rotation":270,"texture":"#0"},"up":{"uv":[10,2,12,4],"rotation":270,"texture":"#0"},"down":{"uv":[10,2,12,4],"rotation":270,"texture":"#0"}}},{"from":[7.82358,21.5,3.11836],"to":[10.57358,23.49,8.86836],"rotation":{"angle":0,"axis":"y","origin":[6.84719,22.375,5.01938]},"faces":{"north":{"uv":[6,8,8,10],"texture":"#0"},"east":{"uv":[6,8,8,10],"texture":"#0"},"south":{"uv":[6,8,8,10],"texture":"#0"},"west":{"uv":[6,8,8,10],"texture":"#0"},"up":{"uv":[6.025,8.025,8.85,9.775],"rotation":270,"texture":"#0"},"down":{"uv":[6,8,8,10],"texture":"#0"}}},{"from":[4.47219,21.5,2.45172],"to":[9.22219,23.5,8.20172],"rotation":{"angle":-22.5,"axis":"y","origin":[6.84719,22.375,5.01938]},"faces":{"north":{"uv":[6,8,8,10],"texture":"#0"},"east":{"uv":[6,8,8,10],"texture":"#0"},"south":{"uv":[6,8,8,10],"texture":"#0"},"west":{"uv":[6,8,8,10],"texture":"#0"},"up":{"uv":[6.25,8,9,10],"rotation":270,"texture":"#0"},"down":{"uv":[6,8,8,10],"texture":"#0"}}},{"from":[3.12081,21.5,3.11836],"to":[5.87081,23.49,8.86836],"rotation":{"angle":-45,"axis":"y","origin":[6.84719,22.375,5.01938]},"faces":{"north":{"uv":[6,8,8,10],"texture":"#0"},"east":{"uv":[6,8,8,10],"texture":"#0"},"south":{"uv":[6,8,8,10],"texture":"#0"},"west":{"uv":[6,8,8,10],"texture":"#0"},"up":{"uv":[6,8,8.85,10],"rotation":270,"texture":"#0"},"down":{"uv":[6,8,8,10],"texture":"#0"}}},{"from":[2.5,-15,1.5],"to":[14.25,-11,14.25],"rotation":{"angle":0,"axis":"y","origin":[0,-26.75,0]},"faces":{"north":{"uv":[4,0,6,2],"texture":"#0"},"east":{"uv":[4,0,6,2],"texture":"#0"},"south":{"uv":[4,0,6,2],"texture":"#0"},"west":{"uv":[4,0,6,2],"texture":"#0"},"up":{"uv":[4,0,6,2],"texture":"#0"},"down":{"uv":[4,0,6,2],"texture":"#0"}}},{"from":[3,-15,14.25],"to":[13.5,-11,15],"rotation":{"angle":0,"axis":"y","origin":[0,-26.75,-0.25]},"faces":{"north":{"uv":[4,0,6,2],"texture":"#0"},"east":{"uv":[4,0,6,2],"texture":"#0"},"south":{"uv":[4,0,6,2],"texture":"#0"},"west":{"uv":[4,0,6,2],"texture":"#0"},"up":{"uv":[4,0,6,2],"texture":"#0"},"down":{"uv":[4,0,6,2],"texture":"#0"}}},{"from":[3,-15,0.75],"to":[13.5,-11,1.5],"rotation":{"angle":0,"axis":"y","origin":[0,-26.75,-0.25]},"faces":{"north":{"uv":[4,0,6,2],"texture":"#0"},"east":{"uv":[4,0,6,2],"texture":"#0"},"south":{"uv":[4,0,6,2],"texture":"#0"},"west":{"uv":[4,0,6,2],"texture":"#0"},"up":{"uv":[4,0,6,2],"texture":"#0"},"down":{"uv":[4,0,6,2],"texture":"#0"}}},{"from":[0.51409,-15,16.73376],"to":[2.26409,-11,17.48376],"rotation":{"angle":-45,"axis":"y","origin":[5.63909,-17.375,17.10876]},"faces":{"north":{"uv":[4,0,6,2],"texture":"#0"},"east":{"uv":[4,0,6,2],"texture":"#0"},"south":{"uv":[4,0,6,2],"texture":"#0"},"west":{"uv":[4,0,6,2],"texture":"#0"},"up":{"uv":[4,0,6,2],"texture":"#0"},"down":{"uv":[4,0,6,2],"texture":"#0"}}},{"from":[-0.99416,-15,-1.00799],"to":[1.13084,-11,-0.25799],"rotation":{"angle":-45,"axis":"y","origin":[4.13084,-17.375,17.36701]},"faces":{"north":{"uv":[4,0,6,2],"texture":"#0"},"east":{"uv":[4,0,6,2],"texture":"#0"},"south":{"uv":[4,0,6,2],"texture":"#0"},"west":{"uv":[4,0,6,2],"texture":"#0"},"up":{"uv":[4,0,6,2],"texture":"#0"},"down":{"uv":[4,0,6,2],"texture":"#0"}}},{"from":[12.92364,-15,13.60853],"to":[15.04864,-11,14.35853],"rotation":{"angle":45,"axis":"y","origin":[13.98614,-17.375,13.98353]},"faces":{"north":{"uv":[4,0,6,2],"texture":"#0"},"east":{"uv":[4,0,6,2],"texture":"#0"},"south":{"uv":[4,0,6,2],"texture":"#0"},"west":{"uv":[4,0,6,2],"texture":"#0"},"up":{"uv":[4,0,6,2],"texture":"#0"},"down":{"uv":[4,0,6,2],"texture":"#0"}}},{"from":[14.52929,-15,-3.88061],"to":[16.30429,-11,-3.13061],"rotation":{"angle":45,"axis":"y","origin":[15.24179,-17.375,14.49439]},"faces":{"north":{"uv":[4,0,6,2],"texture":"#0"},"east":{"uv":[4,0,6,2],"texture":"#0"},"south":{"uv":[4,0,6,2],"texture":"#0"},"west":{"uv":[4,0,6,2],"texture":"#0"},"up":{"uv":[4,0,6,2],"texture":"#0"},"down":{"uv":[4,0,6,2],"texture":"#0"}}},{"from":[1.75,-15,2.025],"to":[2.5,-11,13.75],"rotation":{"angle":0,"axis":"y","origin":[0,-26.75,0]},"faces":{"north":{"uv":[4,0,6,2],"texture":"#0"},"east":{"uv":[4,0,6,2],"texture":"#0"},"south":{"uv":[4,0,6,2],"texture":"#0"},"west":{"uv":[4,0,6,2],"texture":"#0"},"up":{"uv":[4,0,6,2],"texture":"#0"},"down":{"uv":[4,0,6,2],"texture":"#0"}}},{"from":[14.25,-15,2.25],"to":[15,-11,13.5],"rotation":{"angle":0,"axis":"y","origin":[0,-26.75,0]},"faces":{"north":{"uv":[4,0,6,2],"texture":"#0"},"east":{"uv":[4,0,6,2],"texture":"#0"},"south":{"uv":[4,0,6,2],"texture":"#0"},"west":{"uv":[4,0,6,2],"texture":"#0"},"up":{"uv":[4,0,6,2],"texture":"#0"},"down":{"uv":[4,0,6,2],"texture":"#0"}}},{"from":[1.75,-9.25,2.025],"to":[2.5,-5.25,13.75],"rotation":{"angle":0,"axis":"y","origin":[0,-21,0]},"faces":{"north":{"uv":[0,0,2,2],"texture":"#0"},"east":{"uv":[0,0,2,2],"texture":"#0"},"south":{"uv":[0,0,2,2],"texture":"#0"},"west":{"uv":[0,0,2,2],"texture":"#0"},"up":{"uv":[0,0,2,2],"texture":"#0"},"down":{"uv":[0,0,2,2],"texture":"#0"}}},{"from":[14.25,-9.25,2.25],"to":[15,-5.25,13.5],"rotation":{"angle":0,"axis":"y","origin":[0,-21,0]},"faces":{"north":{"uv":[0,0,2,2],"texture":"#0"},"east":{"uv":[0,0,2,2],"texture":"#0"},"south":{"uv":[0,0,2,2],"texture":"#0"},"west":{"uv":[0,0,2,2],"texture":"#0"},"up":{"uv":[0,0,2,2],"texture":"#0"},"down":{"uv":[0,0,2,2],"texture":"#0"}}},{"from":[1.75,-5.25,2.025],"to":[2.5,6,13.75],"rotation":{"angle":0,"axis":"y","origin":[0,-17,0]},"faces":{"north":{"uv":[14,6,16,8],"texture":"#0"},"east":{"uv":[14,6,16,8],"texture":"#0"},"south":{"uv":[14,6,16,8],"texture":"#0"},"west":{"uv":[14,6,16,8],"texture":"#0"},"up":{"uv":[14,6,16,8],"texture":"#0"},"down":{"uv":[14,6,16,8],"texture":"#0"}}},{"from":[14.25,-5.25,2.25],"to":[15,6,13.5],"rotation":{"angle":0,"axis":"y","origin":[0,-17,0]},"faces":{"north":{"uv":[14,6,16,8],"texture":"#0"},"east":{"uv":[14,6,16,8],"texture":"#0"},"south":{"uv":[14,6,16,8],"texture":"#0"},"west":{"uv":[14,6,16,8],"texture":"#0"},"up":{"uv":[14,6,16,8],"texture":"#0"},"down":{"uv":[14,6,16,8],"texture":"#0"}}},{"from":[2.5,17.75,1.5],"to":[14.25,19.5,14.25],"rotation":{"angle":0,"axis":"y","origin":[0,6,0]},"faces":{"north":{"uv":[12,6,14,8],"texture":"#0"},"east":{"uv":[12,6,14,8],"texture":"#0"},"south":{"uv":[12,6,14,8],"texture":"#0"},"west":{"uv":[12,6,14,8],"texture":"#0"},"up":{"uv":[12,6,14,8],"texture":"#0"},"down":{"uv":[12,6,14,8],"texture":"#0"}}},{"from":[1.75,17.75,2.025],"to":[2.5,19.5,13.75],"rotation":{"angle":0,"axis":"y","origin":[0,6,0]},"faces":{"north":{"uv":[12,6,14,8],"texture":"#0"},"east":{"uv":[12,6,14,8],"texture":"#0"},"south":{"uv":[12,6,14,8],"texture":"#0"},"west":{"uv":[12,6,14,8],"texture":"#0"},"up":{"uv":[12,6,14,8],"texture":"#0"},"down":{"uv":[12,6,14,8],"texture":"#0"}}},{"from":[14.25,17.75,2.25],"to":[15,19.5,13.5],"rotation":{"angle":0,"axis":"y","origin":[0,6,0]},"faces":{"north":{"uv":[12,6,14,8],"texture":"#0"},"east":{"uv":[12,6,14,8],"texture":"#0"},"south":{"uv":[12,6,14,8],"texture":"#0"},"west":{"uv":[12,6,14,8],"texture":"#0"},"up":{"uv":[12,6,14,8],"texture":"#0"},"down":{"uv":[12,6,14,8],"texture":"#0"}}},{"from":[1.75,-11,2.025],"to":[2.5,-9.25,13.75],"rotation":{"angle":0,"axis":"y","origin":[0,-22.75,0]},"faces":{"north":{"uv":[4,4,6,6],"texture":"#0"},"east":{"uv":[4,4,6,6],"texture":"#0"},"south":{"uv":[4,4,6,6],"texture":"#0"},"west":{"uv":[4,4,6,6],"texture":"#0"},"up":{"uv":[4,4,6,6],"texture":"#0"},"down":{"uv":[4,4,6,6],"texture":"#0"}}},{"from":[14.25,-11,2.25],"to":[15,-9.25,13.5],"rotation":{"angle":0,"axis":"y","origin":[0,-22.75,0]},"faces":{"north":{"uv":[4,4,6,6],"texture":"#0"},"east":{"uv":[4,4,6,6],"texture":"#0"},"south":{"uv":[4,4,6,6],"texture":"#0"},"west":{"uv":[4,4,6,6],"texture":"#0"},"up":{"uv":[4,4,6,6],"texture":"#0"},"down":{"uv":[4,4,6,6],"texture":"#0"}}},{"from":[2.5,6,1.5],"to":[14.25,10,14.25],"rotation":{"angle":0,"axis":"y","origin":[0,-5.75,0]},"faces":{"north":{"uv":[4,8,6,10],"texture":"#0"},"east":{"uv":[4,8,6,10],"texture":"#0"},"south":{"uv":[4,8,6,10],"texture":"#0"},"west":{"uv":[4,8,6,10],"texture":"#0"},"up":{"uv":[4,8,6,10],"texture":"#0"},"down":{"uv":[4,8,6,10],"texture":"#0"}}},{"from":[1.75,6,2.025],"to":[2.5,10,13.75],"rotation":{"angle":0,"axis":"y","origin":[0,-5.75,0]},"faces":{"north":{"uv":[4,8,6,10],"texture":"#0"},"east":{"uv":[4,8,6,10],"texture":"#0"},"south":{"uv":[4,8,6,10],"texture":"#0"},"west":{"uv":[4,8,6,10],"texture":"#0"},"up":{"uv":[4,8,6,10],"texture":"#0"},"down":{"uv":[4,8,6,10],"texture":"#0"}}},{"from":[14.25,6,2.25],"to":[15,10,13.5],"rotation":{"angle":0,"axis":"y","origin":[0,-5.75,0]},"faces":{"north":{"uv":[4,8,6,10],"texture":"#0"},"east":{"uv":[4,8,6,10],"texture":"#0"},"south":{"uv":[4,8,6,10],"texture":"#0"},"west":{"uv":[4,8,6,10],"texture":"#0"},"up":{"uv":[4,8,6,10],"texture":"#0"},"down":{"uv":[4,8,6,10],"texture":"#0"}}},{"from":[2.5,19.5,1.5],"to":[14.25,21.25,14.25],"rotation":{"angle":0,"axis":"y","origin":[8.375,20.375,7.875]},"faces":{"north":{"uv":[10,6,12,8],"texture":"#0"},"east":{"uv":[10,6,12,8],"texture":"#0"},"south":{"uv":[10,6,12,8],"texture":"#0"},"west":{"uv":[10,6,12,8],"texture":"#0"},"up":{"uv":[10,6,12,8],"texture":"#0"},"down":{"uv":[10,6,12,8],"texture":"#0"}}},{"from":[3,19.5,14.25],"to":[13.5,21.25,15],"rotation":{"angle":0,"axis":"y","origin":[0,7.75,-0.25]},"faces":{"north":{"uv":[10,6,12,8],"texture":"#0"},"east":{"uv":[10,6,12,8],"texture":"#0"},"south":{"uv":[10,6,12,8],"texture":"#0"},"west":{"uv":[10,6,12,8],"texture":"#0"},"up":{"uv":[10,6,12,8],"texture":"#0"},"down":{"uv":[10,6,12,8],"texture":"#0"}}},{"from":[3,19.5,0.75],"to":[13.5,21.25,1.5],"rotation":{"angle":0,"axis":"y","origin":[0,7.75,-0.25]},"faces":{"north":{"uv":[10,6,12,8],"texture":"#0"},"east":{"uv":[10,6,12,8],"texture":"#0"},"south":{"uv":[10,6,12,8],"texture":"#0"},"west":{"uv":[10,6,12,8],"texture":"#0"},"up":{"uv":[10,6,12,8],"texture":"#0"},"down":{"uv":[10,6,12,8],"texture":"#0"}}},{"from":[0.51409,19.5,16.73376],"to":[2.26409,21.25,17.48376],"rotation":{"angle":-45,"axis":"y","origin":[5.63909,17.125,17.10876]},"faces":{"north":{"uv":[10,6,12,8],"texture":"#0"},"east":{"uv":[10,6,12,8],"texture":"#0"},"south":{"uv":[10,6,12,8],"texture":"#0"},"west":{"uv":[10,6,12,8],"texture":"#0"},"up":{"uv":[10,6,12,8],"texture":"#0"},"down":{"uv":[10,6,12,8],"texture":"#0"}}},{"from":[-0.99416,19.5,-1.00799],"to":[1.13084,21.25,-0.25799],"rotation":{"angle":-45,"axis":"y","origin":[4.13084,17.125,17.36701]},"faces":{"north":{"uv":[10,6,12,8],"texture":"#0"},"east":{"uv":[10,6,12,8],"texture":"#0"},"south":{"uv":[10,6,12,8],"texture":"#0"},"west":{"uv":[10,6,12,8],"texture":"#0"},"up":{"uv":[10,6,12,8],"texture":"#0"},"down":{"uv":[10,6,12,8],"texture":"#0"}}},{"from":[12.92364,19.5,13.60853],"to":[15.04864,21.25,14.35853],"rotation":{"angle":45,"axis":"y","origin":[13.98614,17.125,13.98353]},"faces":{"north":{"uv":[10,6,12,8],"texture":"#0"},"east":{"uv":[10,6,12,8],"texture":"#0"},"south":{"uv":[10,6,12,8],"texture":"#0"},"west":{"uv":[10,6,12,8],"texture":"#0"},"up":{"uv":[10,6,12,8],"texture":"#0"},"down":{"uv":[10,6,12,8],"texture":"#0"}}},{"from":[14.52929,19.5,-3.88061],"to":[16.30429,21.25,-3.13061],"rotation":{"angle":45,"axis":"y","origin":[15.24179,17.125,14.49439]},"faces":{"north":{"uv":[10,6,12,8],"texture":"#0"},"east":{"uv":[10,6,12,8],"texture":"#0"},"south":{"uv":[10,6,12,8],"texture":"#0"},"west":{"uv":[10,6,12,8],"texture":"#0"},"up":{"uv":[10,6,12,8],"texture":"#0"},"down":{"uv":[10,6,12,8],"texture":"#0"}}},{"from":[1.75,19.5,2.025],"to":[2.5,21.25,13.75],"rotation":{"angle":0,"axis":"y","origin":[0,7.75,0]},"faces":{"north":{"uv":[10,6,12,8],"texture":"#0"},"east":{"uv":[10,6,12,8],"texture":"#0"},"south":{"uv":[10,6,12,8],"texture":"#0"},"west":{"uv":[10,6,12,8],"texture":"#0"},"up":{"uv":[10,6,12,8],"texture":"#0"},"down":{"uv":[10,6,12,8],"texture":"#0"}}},{"from":[14.25,19.5,2.25],"to":[15,21.25,13.5],"rotation":{"angle":0,"axis":"y","origin":[0,7.75,0]},"faces":{"north":{"uv":[10,6,12,8],"texture":"#0"},"east":{"uv":[10,6,12,8],"texture":"#0"},"south":{"uv":[10,6,12,8],"texture":"#0"},"west":{"uv":[10,6,12,8],"texture":"#0"},"up":{"uv":[10,6,12,8],"texture":"#0"},"down":{"uv":[10,6,12,8],"texture":"#0"}}},{"from":[3.5,10,3.5],"to":[5.25,11.75,5.25],"rotation":{"angle":0,"axis":"y","origin":[0,2,0]},"faces":{"north":{"uv":[8,6,10,8],"texture":"#0"},"east":{"uv":[8,6,10,8],"texture":"#0"},"south":{"uv":[8,6,10,8],"texture":"#0"},"west":{"uv":[8,6,10,8],"texture":"#0"},"up":{"uv":[8,6,10,8],"texture":"#0"},"down":{"uv":[8,6,10,8],"texture":"#0"}}},{"from":[9.5,15.5,4.5],"to":[11.25,17.25,6.25],"rotation":{"angle":22.5,"axis":"z","origin":[10.375,16.375,5.375]},"faces":{"north":{"uv":[8,6,10,8],"texture":"#0"},"east":{"uv":[8,6,10,8],"texture":"#0"},"south":{"uv":[8,6,10,8],"texture":"#0"},"west":{"uv":[8,6,10,8],"texture":"#0"},"up":{"uv":[8,6,10,8],"texture":"#0"},"down":{"uv":[8,6,10,8],"texture":"#0"}}},{"from":[10.5,11,9.5],"to":[13.25,13.75,12.25],"rotation":{"angle":0,"axis":"y","origin":[0,2,0]},"faces":{"north":{"uv":[8,6,10,8],"texture":"#0"},"east":{"uv":[8,6,10,8],"texture":"#0"},"south":{"uv":[8,6,10,8],"texture":"#0"},"west":{"uv":[8,6,10,8],"texture":"#0"},"up":{"uv":[8,6,10,8],"texture":"#0"},"down":{"uv":[8,6,10,8],"texture":"#0"}}},{"from":[4.5,12,7.5],"to":[7.25,14.75,10.25],"rotation":{"angle":-22.5,"axis":"z","origin":[5.875,13.375,8.875]},"faces":{"north":{"uv":[8,6,10,8],"texture":"#0"},"east":{"uv":[8,6,10,8],"texture":"#0"},"south":{"uv":[8,6,10,8],"texture":"#0"},"west":{"uv":[8,6,10,8],"texture":"#0"},"up":{"uv":[8,6,10,8],"texture":"#0"},"down":{"uv":[8,6,10,8],"texture":"#0"}}},{"from":[3,10,14.25],"to":[13.5,17.75,15],"rotation":{"angle":0,"axis":"y","origin":[0,2,-0.25]},"faces":{"north":{"uv":[14,2,16,4],"texture":"#0"},"east":{"uv":[6,2,8,4],"texture":"#0"},"south":{"uv":[6,2,8,4],"texture":"#0"},"west":{"uv":[6,2,8,4],"texture":"#0"},"up":{"uv":[6,2,8,4],"texture":"#0"},"down":{"uv":[6,2,8,4],"texture":"#0"}}},{"from":[3,10,0.75],"to":[13.5,17.75,1.5],"rotation":{"angle":0,"axis":"y","origin":[0,2,-0.25]},"faces":{"north":{"uv":[6,2,8,4],"texture":"#0"},"east":{"uv":[6,2,8,4],"texture":"#0"},"south":{"uv":[14,2,16,4],"texture":"#0"},"west":{"uv":[6,2,8,4],"texture":"#0"},"up":{"uv":[6,2,8,4],"texture":"#0"},"down":{"uv":[6,2,8,4],"texture":"#0"}}},{"from":[0.51409,10,16.73376],"to":[2.26409,17.75,17.48376],"rotation":{"angle":-45,"axis":"y","origin":[5.63909,11.375,17.10876]},"faces":{"north":{"uv":[14,2,16,4],"texture":"#0"},"east":{"uv":[6,2,8,4],"texture":"#0"},"south":{"uv":[6,2,8,4],"texture":"#0"},"west":{"uv":[6,2,8,4],"texture":"#0"},"up":{"uv":[6,2,8,4],"texture":"#0"},"down":{"uv":[6,2,8,4],"texture":"#0"}}},{"from":[-0.99416,10,-1.00799],"to":[1.13084,17.75,-0.25799],"rotation":{"angle":-45,"axis":"y","origin":[4.13084,11.375,17.36701]},"faces":{"north":{"uv":[6,2,8,4],"texture":"#0"},"east":{"uv":[6,2,8,4],"texture":"#0"},"south":{"uv":[14,2,16,4],"texture":"#0"},"west":{"uv":[6,2,8,4],"texture":"#0"},"up":{"uv":[6,2,8,4],"texture":"#0"},"down":{"uv":[6,2,8,4],"texture":"#0"}}},{"from":[12.92364,10,13.60853],"to":[15.04864,17.75,14.35853],"rotation":{"angle":45,"axis":"y","origin":[13.98614,11.375,13.98353]},"faces":{"north":{"uv":[14,2,16,4],"texture":"#0"},"east":{"uv":[6,2,8,4],"texture":"#0"},"south":{"uv":[6,2,8,4],"texture":"#0"},"west":{"uv":[6,2,8,4],"texture":"#0"},"up":{"uv":[6,2,8,4],"texture":"#0"},"down":{"uv":[6,2,8,4],"texture":"#0"}}},{"from":[14.52929,10,-3.88061],"to":[16.30429,17.75,-3.13061],"rotation":{"angle":45,"axis":"y","origin":[15.24179,11.375,14.49439]},"faces":{"north":{"uv":[6,2,8,4],"texture":"#0"},"east":{"uv":[6,2,8,4],"texture":"#0"},"south":{"uv":[14,2,16,4],"texture":"#0"},"west":{"uv":[6,2,8,4],"texture":"#0"},"up":{"uv":[6,2,8,4],"texture":"#0"},"down":{"uv":[6,2,8,4],"texture":"#0"}}},{"from":[1.75,10,2.025],"to":[2.5,17.75,13.75],"rotation":{"angle":0,"axis":"y","origin":[0,2,0]},"faces":{"north":{"uv":[6,2,8,4],"texture":"#0"},"east":{"uv":[14,2,16,4],"texture":"#0"},"south":{"uv":[6,2,8,4],"texture":"#0"},"west":{"uv":[6,2,8,4],"texture":"#0"},"up":{"uv":[6,2,8,4],"texture":"#0"},"down":{"uv":[6,2,8,4],"texture":"#0"}}},{"from":[14.25,10,2.25],"to":[15,17.75,13.5],"rotation":{"angle":0,"axis":"y","origin":[0,2,0]},"faces":{"north":{"uv":[6,2,8,4],"texture":"#0"},"east":{"uv":[6,2,8,4],"texture":"#0"},"south":{"uv":[6,2,8,4],"texture":"#0"},"west":{"uv":[14,2,16,4],"texture":"#0"},"up":{"uv":[6,2,8,4],"texture":"#0"},"down":{"uv":[6,2,8,4],"texture":"#0"}}},{"from":[3.25,-15,0],"to":[13.25,23,1],"rotation":{"angle":0,"axis":"y","origin":[0.25,-15.5,0]},"faces":{"north":{"uv":[0.875,6.75,3.1,15.25],"texture":"#0"},"east":{"uv":[14,2,16,4],"texture":"#0"},"south":{"uv":[14,2,16,4],"texture":"#0"},"west":{"uv":[14,2,16,4],"texture":"#0"},"up":{"uv":[12,0,14,2],"texture":"#0"},"down":{"uv":[12,0,14,2],"texture":"#0"}}},{"from":[3.25,-15,15],"to":[13.25,23,16],"rotation":{"angle":0,"axis":"y","origin":[8.25,-7,4.5]},"faces":{"north":{"uv":[14,2,16,4],"texture":"#0"},"east":{"uv":[14,2,16,4],"texture":"#0"},"south":{"uv":[0.875,6.75,3.1,15.25],"texture":"#0"},"west":{"uv":[14,2,16,4],"texture":"#0"},"up":{"uv":[12,0,14,2],"rotation":180,"texture":"#0"},"down":{"uv":[12,0,14,2],"rotation":180,"texture":"#0"}}},{"from":[0.25,-15,3],"to":[1.25,23,13],"rotation":{"angle":0,"axis":"y","origin":[8.25,-14.5,8.5]},"faces":{"north":{"uv":[14,2,16,4],"texture":"#0"},"east":{"uv":[14,2,16,4],"texture":"#0"},"south":{"uv":[14,2,16,4],"texture":"#0"},"west":{"uv":[0.9,6.75,3.125,15.25],"texture":"#0"},"up":{"uv":[12,0,14,2],"texture":"#0"},"down":{"uv":[12,0,14,2],"texture":"#0"}}},{"from":[15.2552,-15,2.9948],"to":[16.2552,23,12.9948],"rotation":{"angle":0,"axis":"y","origin":[-4.2448,-7,7.9948]},"faces":{"north":{"uv":[14,2,16,4],"texture":"#0"},"east":{"uv":[0.9,6.75,3.125,15.25],"texture":"#0"},"south":{"uv":[14,2,16,4],"texture":"#0"},"west":{"uv":[14,2,16,4],"texture":"#0"},"up":{"uv":[12,0,14,2],"rotation":180,"texture":"#0"},"down":{"uv":[12,0,14,2],"rotation":180,"texture":"#0"}}},{"from":[-0.01884,-15,1.35095],"to":[4.23116,23,2.35095],"rotation":{"angle":45,"axis":"y","origin":[2.10616,-14.5,1.85095]},"faces":{"north":{"uv":[0.75,6.75,3.25,15.25],"texture":"#0"},"east":{"uv":[14,2,16,4],"texture":"#0"},"south":{"uv":[14,2,16,4],"texture":"#0"},"west":{"uv":[14,2,16,4],"texture":"#0"},"up":{"uv":[12,0,14,2],"texture":"#0"},"down":{"uv":[12,0,14,2],"texture":"#0"}}},{"from":[18.58534,-15,0.70514],"to":[19.58534,23,4.95514],"rotation":{"angle":-45,"axis":"y","origin":[3.08534,-7,2.83014]},"faces":{"north":{"uv":[14,2,16,4],"texture":"#0"},"east":{"uv":[0.75,6.75,3.25,15.25],"texture":"#0"},"south":{"uv":[14,2,16,4],"texture":"#0"},"west":{"uv":[14,2,16,4],"texture":"#0"},"up":{"uv":[12,0,14,2],"rotation":90,"texture":"#0"},"down":{"uv":[12,0,14,2],"rotation":270,"texture":"#0"}}},{"from":[11.72056,-15,21.30761],"to":[15.97056,23,22.30761],"rotation":{"angle":-45,"axis":"y","origin":[17.22056,-14.5,3.80761]},"faces":{"north":{"uv":[14,2,16,4],"texture":"#0"},"east":{"uv":[14,2,16,4],"texture":"#0"},"south":{"uv":[0.75,6.75,3.25,15.25],"texture":"#0"},"west":{"uv":[14,2,16,4],"texture":"#0"},"up":{"uv":[12,0,14,2],"texture":"#0"},"down":{"uv":[12,0,14,2],"texture":"#0"}}},{"from":[12.27405,-15,1.35616],"to":[16.52405,23,2.35616],"rotation":{"angle":-45,"axis":"y","origin":[14.39905,-7,1.85616]},"faces":{"north":{"uv":[0.75,6.75,3.25,15.25],"texture":"#0"},"east":{"uv":[14,2,16,4],"texture":"#0"},"south":{"uv":[14,2,16,4],"texture":"#0"},"west":{"uv":[14,2,16,4],"texture":"#0"},"up":{"uv":[12,0,14,2],"rotation":180,"texture":"#0"},"down":{"uv":[12,0,14,2],"rotation":180,"texture":"#0"}}},{"from":[3.22056,-16,13.44264],"to":[5.39556,-15,16.24264],"rotation":{"angle":-45,"axis":"y","origin":[18.22056,-15.5,7.24264]},"faces":{"north":{"uv":[14,2,16,4],"texture":"#0"},"east":{"uv":[14,2,16,4],"texture":"#0"},"south":{"uv":[14,2,16,4],"texture":"#0"},"west":{"uv":[12,0,14,2],"texture":"#0"},"up":{"uv":[0,7,2,9],"texture":"#0"},"down":{"uv":[12,0,14,2],"texture":"#0"}}},{"from":[18.20781,-16,12.97988],"to":[20.38281,-15,15.77988],"rotation":{"angle":-45,"axis":"y","origin":[17.75781,-15.5,6.77988]},"faces":{"north":{"uv":[14,2,16,4],"texture":"#0"},"east":{"uv":[12,0,14,2],"texture":"#0"},"south":{"uv":[14,2,16,4],"texture":"#0"},"west":{"uv":[14,2,16,4],"texture":"#0"},"up":{"uv":[2,7,4,9],"texture":"#0"},"down":{"uv":[12,0,14,2],"texture":"#0"}}},{"from":[13.62094,-16,4.34645],"to":[15.79594,-15,7.14645],"rotation":{"angle":45,"axis":"y","origin":[10.48344,-15.5,5.74645]},"faces":{"north":{"uv":[14,2,16,4],"texture":"#0"},"east":{"uv":[12,0,14,2],"texture":"#0"},"south":{"uv":[14,2,16,4],"texture":"#0"},"west":{"uv":[14,2,16,4],"texture":"#0"},"up":{"uv":[2,7,4,9],"texture":"#0"},"down":{"uv":[12,0,14,2],"texture":"#0"}}},{"from":[-1.65919,-16,3.17659],"to":[0.51581,-15,5.97659],"rotation":{"angle":45,"axis":"y","origin":[11.65331,-15.5,4.57659]},"faces":{"north":{"uv":[14,2,16,4],"texture":"#0"},"east":{"uv":[14,2,16,4],"texture":"#0"},"south":{"uv":[14,2,16,4],"texture":"#0"},"west":{"uv":[12,0,14,2],"texture":"#0"},"up":{"uv":[0,7,2,9],"texture":"#0"},"down":{"uv":[12,0,14,2],"texture":"#0"}}},{"from":[1.25,-16,3],"to":[3.25,-15,13],"rotation":{"angle":0,"axis":"y","origin":[0.25,-16,0]},"faces":{"north":{"uv":[14,2,16,4],"texture":"#0"},"east":{"uv":[14,2,16,4],"texture":"#0"},"south":{"uv":[14,2,16,4],"texture":"#0"},"west":{"uv":[12,0,14,2],"texture":"#0"},"up":{"uv":[0,7,2,9],"texture":"#0"},"down":{"uv":[12,0,14,2],"texture":"#0"}}},{"from":[13.25,-16,3],"to":[15.25,-15,13],"rotation":{"angle":0,"axis":"y","origin":[0.25,-16,0]},"faces":{"north":{"uv":[14,2,16,4],"texture":"#0"},"east":{"uv":[12,0,14,2],"texture":"#0"},"south":{"uv":[14,2,16,4],"texture":"#0"},"west":{"uv":[14,2,16,4],"texture":"#0"},"up":{"uv":[2,7,4,9],"texture":"#0"},"down":{"uv":[12,0,14,2],"texture":"#0"}}},{"from":[3.25,-16,1],"to":[13.25,-15,15],"rotation":{"angle":0,"axis":"y","origin":[0.25,-16,0]},"faces":{"north":{"uv":[12,0,14,2],"texture":"#0"},"east":{"uv":[14,2,16,4],"texture":"#0"},"south":{"uv":[12,0,14,2],"texture":"#0"},"west":{"uv":[14,2,16,4],"texture":"#0"},"up":{"uv":[1,6,3,16],"texture":"#0"},"down":{"uv":[12,0,14,2],"texture":"#0"}}},{"from":[2.5,-9.25,1.5],"to":[14.25,-5.25,14.25],"rotation":{"angle":0,"axis":"y","origin":[0,-21,0]},"faces":{"north":{"uv":[0,0,2,2],"texture":"#0"},"east":{"uv":[0,0,2,2],"texture":"#0"},"south":{"uv":[0,0,2,2],"texture":"#0"},"west":{"uv":[0,0,2,2],"texture":"#0"},"up":{"uv":[0,0,2,2],"texture":"#0"},"down":{"uv":[0,0,2,2],"texture":"#0"}}},{"from":[3,-9.25,14.25],"to":[13.5,-5.25,15],"rotation":{"angle":0,"axis":"y","origin":[0,-21,-0.25]},"faces":{"north":{"uv":[0,0,2,2],"texture":"#0"},"east":{"uv":[0,0,2,2],"texture":"#0"},"south":{"uv":[0,0,2,2],"texture":"#0"},"west":{"uv":[0,0,2,2],"texture":"#0"},"up":{"uv":[0,0,2,2],"texture":"#0"},"down":{"uv":[0,0,2,2],"texture":"#0"}}},{"from":[3,-9.25,0.75],"to":[13.5,-5.25,1.5],"rotation":{"angle":0,"axis":"y","origin":[0,-21,-0.25]},"faces":{"north":{"uv":[0,0,2,2],"texture":"#0"},"east":{"uv":[0,0,2,2],"texture":"#0"},"south":{"uv":[0,0,2,2],"texture":"#0"},"west":{"uv":[0,0,2,2],"texture":"#0"},"up":{"uv":[0,0,2,2],"texture":"#0"},"down":{"uv":[0,0,2,2],"texture":"#0"}}},{"from":[0.51409,-9.25,16.73376],"to":[2.26409,-5.25,17.48376],"rotation":{"angle":-45,"axis":"y","origin":[5.63909,-11.625,17.10876]},"faces":{"north":{"uv":[0,0,2,2],"texture":"#0"},"east":{"uv":[0,0,2,2],"texture":"#0"},"south":{"uv":[0,0,2,2],"texture":"#0"},"west":{"uv":[0,0,2,2],"texture":"#0"},"up":{"uv":[0,0,2,2],"texture":"#0"},"down":{"uv":[0,0,2,2],"texture":"#0"}}},{"from":[-0.99416,-9.25,-1.00799],"to":[1.13084,-5.25,-0.25799],"rotation":{"angle":-45,"axis":"y","origin":[4.13084,-11.625,17.36701]},"faces":{"north":{"uv":[0,0,2,2],"texture":"#0"},"east":{"uv":[0,0,2,2],"texture":"#0"},"south":{"uv":[0,0,2,2],"texture":"#0"},"west":{"uv":[0,0,2,2],"texture":"#0"},"up":{"uv":[0,0,2,2],"texture":"#0"},"down":{"uv":[0,0,2,2],"texture":"#0"}}},{"from":[12.92364,-9.25,13.60853],"to":[15.04864,-5.25,14.35853],"rotation":{"angle":45,"axis":"y","origin":[13.98614,-11.625,13.98353]},"faces":{"north":{"uv":[0,0,2,2],"texture":"#0"},"east":{"uv":[0,0,2,2],"texture":"#0"},"south":{"uv":[0,0,2,2],"texture":"#0"},"west":{"uv":[0,0,2,2],"texture":"#0"},"up":{"uv":[0,0,2,2],"texture":"#0"},"down":{"uv":[0,0,2,2],"texture":"#0"}}},{"from":[14.52929,-9.25,-3.88061],"to":[16.30429,-5.25,-3.13061],"rotation":{"angle":45,"axis":"y","origin":[15.24179,-11.625,14.49439]},"faces":{"north":{"uv":[0,0,2,2],"texture":"#0"},"east":{"uv":[0,0,2,2],"texture":"#0"},"south":{"uv":[0,0,2,2],"texture":"#0"},"west":{"uv":[0,0,2,2],"texture":"#0"},"up":{"uv":[0,0,2,2],"texture":"#0"},"down":{"uv":[0,0,2,2],"texture":"#0"}}},{"from":[2.5,-5.25,1.5],"to":[14.25,6,14.25],"rotation":{"angle":0,"axis":"y","origin":[0,-17,0]},"faces":{"north":{"uv":[14,6,16,8],"texture":"#0"},"east":{"uv":[14,6,16,8],"texture":"#0"},"south":{"uv":[14,6,16,8],"texture":"#0"},"west":{"uv":[14,6,16,8],"texture":"#0"},"up":{"uv":[14,6,16,8],"texture":"#0"},"down":{"uv":[14,6,16,8],"texture":"#0"}}},{"from":[3,-5.25,14.25],"to":[13.5,6,15],"rotation":{"angle":0,"axis":"y","origin":[0,-17,-0.25]},"faces":{"north":{"uv":[14,6,16,8],"texture":"#0"},"east":{"uv":[14,6,16,8],"texture":"#0"},"south":{"uv":[14,6,16,8],"texture":"#0"},"west":{"uv":[14,6,16,8],"texture":"#0"},"up":{"uv":[14,6,16,8],"texture":"#0"},"down":{"uv":[14,6,16,8],"texture":"#0"}}},{"from":[3,-5.25,0.75],"to":[13.5,6,1.5],"rotation":{"angle":0,"axis":"y","origin":[0,-17,-0.25]},"faces":{"north":{"uv":[14,6,16,8],"texture":"#0"},"east":{"uv":[14,6,16,8],"texture":"#0"},"south":{"uv":[14,6,16,8],"texture":"#0"},"west":{"uv":[14,6,16,8],"texture":"#0"},"up":{"uv":[14,6,16,8],"texture":"#0"},"down":{"uv":[14,6,16,8],"texture":"#0"}}},{"from":[0.51409,-5.25,16.73376],"to":[2.26409,6,17.48376],"rotation":{"angle":-45,"axis":"y","origin":[5.63909,-7.625,17.10876]},"faces":{"north":{"uv":[14,6,16,8],"texture":"#0"},"east":{"uv":[14,6,16,8],"texture":"#0"},"south":{"uv":[14,6,16,8],"texture":"#0"},"west":{"uv":[14,6,16,8],"texture":"#0"},"up":{"uv":[14,6,16,8],"texture":"#0"},"down":{"uv":[14,6,16,8],"texture":"#0"}}},{"from":[-0.99416,-5.25,-1.00799],"to":[1.13084,6,-0.25799],"rotation":{"angle":-45,"axis":"y","origin":[4.13084,-7.625,17.36701]},"faces":{"north":{"uv":[14,6,16,8],"texture":"#0"},"east":{"uv":[14,6,16,8],"texture":"#0"},"south":{"uv":[14,6,16,8],"texture":"#0"},"west":{"uv":[14,6,16,8],"texture":"#0"},"up":{"uv":[14,6,16,8],"texture":"#0"},"down":{"uv":[14,6,16,8],"texture":"#0"}}},{"from":[12.92364,-5.25,13.60853],"to":[15.04864,6,14.35853],"rotation":{"angle":45,"axis":"y","origin":[13.98614,-7.625,13.98353]},"faces":{"north":{"uv":[14,6,16,8],"texture":"#0"},"east":{"uv":[14,6,16,8],"texture":"#0"},"south":{"uv":[14,6,16,8],"texture":"#0"},"west":{"uv":[14,6,16,8],"texture":"#0"},"up":{"uv":[14,6,16,8],"texture":"#0"},"down":{"uv":[14,6,16,8],"texture":"#0"}}},{"from":[14.52929,-5.25,-3.88061],"to":[16.30429,6,-3.13061],"rotation":{"angle":45,"axis":"y","origin":[15.24179,-7.625,14.49439]},"faces":{"north":{"uv":[14,6,16,8],"texture":"#0"},"east":{"uv":[14,6,16,8],"texture":"#0"},"south":{"uv":[14,6,16,8],"texture":"#0"},"west":{"uv":[14,6,16,8],"texture":"#0"},"up":{"uv":[14,6,16,8],"texture":"#0"},"down":{"uv":[14,6,16,8],"texture":"#0"}}},{"from":[3,17.75,14.25],"to":[13.5,19.5,15],"rotation":{"angle":0,"axis":"y","origin":[0,6,-0.25]},"faces":{"north":{"uv":[12,6,14,8],"texture":"#0"},"east":{"uv":[12,6,14,8],"texture":"#0"},"south":{"uv":[12,6,14,8],"texture":"#0"},"west":{"uv":[12,6,14,8],"texture":"#0"},"up":{"uv":[12,6,14,8],"texture":"#0"},"down":{"uv":[12,6,14,8],"texture":"#0"}}},{"from":[3,17.75,0.75],"to":[13.5,19.5,1.5],"rotation":{"angle":0,"axis":"y","origin":[0,6,-0.25]},"faces":{"north":{"uv":[12,6,14,8],"texture":"#0"},"east":{"uv":[12,6,14,8],"texture":"#0"},"south":{"uv":[12,6,14,8],"texture":"#0"},"west":{"uv":[12,6,14,8],"texture":"#0"},"up":{"uv":[12,6,14,8],"texture":"#0"},"down":{"uv":[12,6,14,8],"texture":"#0"}}},{"from":[0.51409,17.75,16.73376],"to":[2.26409,19.5,17.48376],"rotation":{"angle":-45,"axis":"y","origin":[5.63909,15.375,17.10876]},"faces":{"north":{"uv":[12,6,14,8],"texture":"#0"},"east":{"uv":[12,6,14,8],"texture":"#0"},"south":{"uv":[12,6,14,8],"texture":"#0"},"west":{"uv":[12,6,14,8],"texture":"#0"},"up":{"uv":[12,6,14,8],"texture":"#0"},"down":{"uv":[12,6,14,8],"texture":"#0"}}},{"from":[-0.99416,17.75,-1.00799],"to":[1.13084,19.5,-0.25799],"rotation":{"angle":-45,"axis":"y","origin":[4.13084,15.375,17.36701]},"faces":{"north":{"uv":[12,6,14,8],"texture":"#0"},"east":{"uv":[12,6,14,8],"texture":"#0"},"south":{"uv":[12,6,14,8],"texture":"#0"},"west":{"uv":[12,6,14,8],"texture":"#0"},"up":{"uv":[12,6,14,8],"texture":"#0"},"down":{"uv":[12,6,14,8],"texture":"#0"}}},{"from":[12.92364,17.75,13.60853],"to":[15.04864,19.5,14.35853],"rotation":{"angle":45,"axis":"y","origin":[13.98614,15.375,13.98353]},"faces":{"north":{"uv":[12,6,14,8],"texture":"#0"},"east":{"uv":[12,6,14,8],"texture":"#0"},"south":{"uv":[12,6,14,8],"texture":"#0"},"west":{"uv":[12,6,14,8],"texture":"#0"},"up":{"uv":[12,6,14,8],"texture":"#0"},"down":{"uv":[12,6,14,8],"texture":"#0"}}},{"from":[14.52929,17.75,-3.88061],"to":[16.30429,19.5,-3.13061],"rotation":{"angle":45,"axis":"y","origin":[15.24179,15.375,14.49439]},"faces":{"north":{"uv":[12,6,14,8],"texture":"#0"},"east":{"uv":[12,6,14,8],"texture":"#0"},"south":{"uv":[12,6,14,8],"texture":"#0"},"west":{"uv":[12,6,14,8],"texture":"#0"},"up":{"uv":[12,6,14,8],"texture":"#0"},"down":{"uv":[12,6,14,8],"texture":"#0"}}},{"from":[2.5,-11,1.5],"to":[14.25,-9.25,14.25],"rotation":{"angle":0,"axis":"y","origin":[0,-22.75,0]},"faces":{"north":{"uv":[4,4,6,6],"texture":"#0"},"east":{"uv":[4,4,6,6],"texture":"#0"},"south":{"uv":[4,4,6,6],"texture":"#0"},"west":{"uv":[4,4,6,6],"texture":"#0"},"up":{"uv":[4,4,6,6],"texture":"#0"},"down":{"uv":[4,4,6,6],"texture":"#0"}}},{"from":[3,-11,14.25],"to":[13.5,-9.25,15],"rotation":{"angle":0,"axis":"y","origin":[0,-22.75,-0.25]},"faces":{"north":{"uv":[4,4,6,6],"texture":"#0"},"east":{"uv":[4,4,6,6],"texture":"#0"},"south":{"uv":[4,4,6,6],"texture":"#0"},"west":{"uv":[4,4,6,6],"texture":"#0"},"up":{"uv":[4,4,6,6],"texture":"#0"},"down":{"uv":[4,4,6,6],"texture":"#0"}}},{"from":[3,-11,0.75],"to":[13.5,-9.25,1.5],"rotation":{"angle":0,"axis":"y","origin":[0,-22.75,-0.25]},"faces":{"north":{"uv":[4,4,6,6],"texture":"#0"},"east":{"uv":[4,4,6,6],"texture":"#0"},"south":{"uv":[4,4,6,6],"texture":"#0"},"west":{"uv":[4,4,6,6],"texture":"#0"},"up":{"uv":[4,4,6,6],"texture":"#0"},"down":{"uv":[4,4,6,6],"texture":"#0"}}},{"from":[0.51409,-11,16.73376],"to":[2.26409,-9.25,17.48376],"rotation":{"angle":-45,"axis":"y","origin":[5.63909,-13.375,17.10876]},"faces":{"north":{"uv":[4,4,6,6],"texture":"#0"},"east":{"uv":[4,4,6,6],"texture":"#0"},"south":{"uv":[4,4,6,6],"texture":"#0"},"west":{"uv":[4,4,6,6],"texture":"#0"},"up":{"uv":[4,4,6,6],"texture":"#0"},"down":{"uv":[4,4,6,6],"texture":"#0"}}},{"from":[-0.99416,-11,-1.00799],"to":[1.13084,-9.25,-0.25799],"rotation":{"angle":-45,"axis":"y","origin":[4.13084,-13.375,17.36701]},"faces":{"north":{"uv":[4,4,6,6],"texture":"#0"},"east":{"uv":[4,4,6,6],"texture":"#0"},"south":{"uv":[4,4,6,6],"texture":"#0"},"west":{"uv":[4,4,6,6],"texture":"#0"},"up":{"uv":[4,4,6,6],"texture":"#0"},"down":{"uv":[4,4,6,6],"texture":"#0"}}},{"from":[12.92364,-11,13.60853],"to":[15.04864,-9.25,14.35853],"rotation":{"angle":45,"axis":"y","origin":[13.98614,-13.375,13.98353]},"faces":{"north":{"uv":[4,4,6,6],"texture":"#0"},"east":{"uv":[4,4,6,6],"texture":"#0"},"south":{"uv":[4,4,6,6],"texture":"#0"},"west":{"uv":[4,4,6,6],"texture":"#0"},"up":{"uv":[4,4,6,6],"texture":"#0"},"down":{"uv":[4,4,6,6],"texture":"#0"}}},{"from":[14.52929,-11,-3.88061],"to":[16.30429,-9.25,-3.13061],"rotation":{"angle":45,"axis":"y","origin":[15.24179,-13.375,14.49439]},"faces":{"north":{"uv":[4,4,6,6],"texture":"#0"},"east":{"uv":[4,4,6,6],"texture":"#0"},"south":{"uv":[4,4,6,6],"texture":"#0"},"west":{"uv":[4,4,6,6],"texture":"#0"},"up":{"uv":[4,4,6,6],"texture":"#0"},"down":{"uv":[4,4,6,6],"texture":"#0"}}},{"from":[3,6,14.25],"to":[13.5,10,15],"rotation":{"angle":0,"axis":"y","origin":[0,-5.75,-0.25]},"faces":{"north":{"uv":[4,8,6,10],"texture":"#0"},"east":{"uv":[4,8,6,10],"texture":"#0"},"south":{"uv":[4,8,6,10],"texture":"#0"},"west":{"uv":[4,8,6,10],"texture":"#0"},"up":{"uv":[4,8,6,10],"texture":"#0"},"down":{"uv":[4,8,6,10],"texture":"#0"}}},{"from":[3,6,0.75],"to":[13.5,10,1.5],"rotation":{"angle":0,"axis":"y","origin":[0,-5.75,-0.25]},"faces":{"north":{"uv":[4,8,6,10],"texture":"#0"},"east":{"uv":[4,8,6,10],"texture":"#0"},"south":{"uv":[4,8,6,10],"texture":"#0"},"west":{"uv":[4,8,6,10],"texture":"#0"},"up":{"uv":[4,8,6,10],"texture":"#0"},"down":{"uv":[4,8,6,10],"texture":"#0"}}},{"from":[0.51409,6,16.73376],"to":[2.26409,10,17.48376],"rotation":{"angle":-45,"axis":"y","origin":[5.63909,3.625,17.10876]},"faces":{"north":{"uv":[4,8,6,10],"texture":"#0"},"east":{"uv":[4,8,6,10],"texture":"#0"},"south":{"uv":[4,8,6,10],"texture":"#0"},"west":{"uv":[4,8,6,10],"texture":"#0"},"up":{"uv":[4,8,6,10],"texture":"#0"},"down":{"uv":[4,8,6,10],"texture":"#0"}}},{"from":[-0.99416,6,-1.00799],"to":[1.13084,10,-0.25799],"rotation":{"angle":-45,"axis":"y","origin":[4.13084,3.625,17.36701]},"faces":{"north":{"uv":[4,8,6,10],"texture":"#0"},"east":{"uv":[4,8,6,10],"texture":"#0"},"south":{"uv":[4,8,6,10],"texture":"#0"},"west":{"uv":[4,8,6,10],"texture":"#0"},"up":{"uv":[4,8,6,10],"texture":"#0"},"down":{"uv":[4,8,6,10],"texture":"#0"}}},{"from":[12.92364,6,13.60853],"to":[15.04864,10,14.35853],"rotation":{"angle":45,"axis":"y","origin":[13.98614,3.625,13.98353]},"faces":{"north":{"uv":[4,8,6,10],"texture":"#0"},"east":{"uv":[4,8,6,10],"texture":"#0"},"south":{"uv":[4,8,6,10],"texture":"#0"},"west":{"uv":[4,8,6,10],"texture":"#0"},"up":{"uv":[4,8,6,10],"texture":"#0"},"down":{"uv":[4,8,6,10],"texture":"#0"}}},{"from":[14.52929,6,-3.88061],"to":[16.30429,10,-3.13061],"rotation":{"angle":45,"axis":"y","origin":[15.24179,3.625,14.49439]},"faces":{"north":{"uv":[4,8,6,10],"texture":"#0"},"east":{"uv":[4,8,6,10],"texture":"#0"},"south":{"uv":[4,8,6,10],"texture":"#0"},"west":{"uv":[4,8,6,10],"texture":"#0"},"up":{"uv":[4,8,6,10],"texture":"#0"},"down":{"uv":[4,8,6,10],"texture":"#0"}}},{"from":[0.25,-15,3],"to":[1.25,23,13],"rotation":{"angle":0,"axis":"y","origin":[8.25,-14.5,8.5]},"faces":{"north":{"uv":[14,2,16,4],"texture":"#0"},"east":{"uv":[14,2,16,4],"texture":"#0"},"south":{"uv":[14,2,16,4],"texture":"#0"},"west":{"uv":[0.9,6.75,3.125,15.25],"texture":"#0"},"up":{"uv":[12,0,14,2],"texture":"#0"},"down":{"uv":[12,0,14,2],"texture":"#0"}}}],"gui_light":"front","display":{"thirdperson_righthand":{"translation":[0,2.75,-1],"scale":[0.2,0.2,0.2]},"thirdperson_lefthand":{"rotation":[0,180,0],"translation":[0,2.5,-1.75],"scale":[0.3,0.3,0.3]},"firstperson_righthand":{"rotation":[0,135,0],"translation":[2,0.25,0],"scale":[0.3,0.3,0.3]},"firstperson_lefthand":{"rotation":[0,135,0],"translation":[12,-4.5,-9.25],"scale":[0.5,0.5,0.5]},"ground":{"translation":[0,4.25,0],"scale":[0.3,0.3,0.3]},"gui":{"rotation":[30,135,0],"translation":[0,1,0],"scale":[0.3,0.3,0.3]},"head":{"rotation":[30,0,0],"translation":[0,-7.5,-7.5],"scale":[0.3,0.3,0.3]},"fixed":{"rotation":[-90,0,0],"translation":[0,0,-12.5],"scale":[0.5,0.5,0.5]}},"groups":[{"name":"otama","origin":[8.25,-14.5,8.5],"color":0,"children":[0,1,2,3,4,5]},{"name":"ue","origin":[8,8,8],"color":0,"children":[6,7,8,9,10,11,12,13,14,15,16,17,18,19,20]},{"name":"cream","origin":[8,8,8],"color":0,"children":[{"name":"nakami_bw","origin":[8,8,8],"color":0,"children":[21,22,23,24,25,26,27,28,29]},{"name":"nakami_bl","origin":[8,8,8],"color":0,"children":[30,31]},{"name":"nakami_blwn","origin":[8,8,8],"color":0,"children":[32,33]},{"name":"nakami_o","origin":[8,8,8],"color":0,"children":[34,35,36]},{"name":"nakami_w","origin":[8,8,8],"color":0,"children":[37,38]},{"name":"nakami_y","origin":[8,8,8],"color":0,"children":[39,40,41]},{"name":"nakami_dr","origin":[8,8,8],"color":0,"children":[42,43,44,45,46,47,48,49,50]},{"name":"nakami_r","origin":[8,8,8],"color":0,"children":[51,52,53,54,55,56,57,58,59,60,61,62]}]},{"name":"cup","origin":[8,8,8],"color":0,"children":[{"name":"gawa","origin":[8,8,8],"color":0,"children":[63,64,65,66,67,68,69,70]},{"name":"soko","origin":[8,8,8],"color":0,"children":[71,72,73,74,75,76,77]}]},78,79,80,81,82,83,84,85,86,87,88,89,90,91,92,93,94,95,96,97,98,99,100,101,102,103,104,105,106,107,108,109,110,111]}